trivrepr/__init__.py
trivrepr/py.typed
trivrepr-0.2.1.dist-info/METADATA
trivrepr-0.2.1.dist-info/WHEEL
trivrepr-0.2.1.dist-info/RECORD
