Metadata-Version: 2.3
Name: trivrepr
Version: 0.2.1
Summary: Provide a helper for creating repr() strings
Project-URL: Homepage, https://devel.ringlet.net/devel/trivrepr/
Project-URL: Changelog, https://devel.ringlet.net/devel/trivrepr/changes/
Project-URL: Repository, https://gitlab.com/ppentchev/trivrepr
Author-email: Peter Pentchev <roam@ringlet.net>
License: BSD-2-Clause
Classifier: Development Status :: 5 - Production/Stable
Classifier: Intended Audience :: Developers
Classifier: License :: DFSG approved
Classifier: License :: Freely Distributable
Classifier: License :: OSI Approved :: BSD License
Classifier: Operating System :: OS Independent
Classifier: Programming Language :: Python
Classifier: Programming Language :: Python :: 3
Classifier: Programming Language :: Python :: 3 :: Only
Classifier: Programming Language :: Python :: 3.9
Classifier: Programming Language :: Python :: 3.10
Classifier: Programming Language :: Python :: 3.11
Classifier: Programming Language :: Python :: 3.12
Classifier: Programming Language :: Python :: 3.13
Classifier: Topic :: Software Development :: Libraries
Classifier: Topic :: Software Development :: Libraries :: Python Modules
Requires-Python: >=3.9
